arith_unit_26_rtl.sv
/* Generated by Yosys 0.34 (git sha1 4a1b5599258, gcc 13.2.1 -march=x86-64 -mtune=generic -O2 -fno-plt -fexceptions -fstack-clash-protection -fcf-protection -ffile-prefix-map=/build/yosys/src=/usr/src/debug/yosys -fPIC -Os) */

module arith_unit_26_rtl(i_op, i_arg_A, i_arg_B, i_clk, i_reset, o_result, o_status);
  wire _000_;
  wire _001_;
  wire _002_;
  wire _003_;
  wire _004_;
  wire _005_;
  wire _006_;
  wire _007_;
  wire _008_;
  wire _009_;
  wire _010_;
  wire _011_;
  wire _012_;
  wire _013_;
  wire _014_;
  wire _015_;
  wire _016_;
  wire _017_;
  wire _018_;
  wire _019_;
  wire _020_;
  wire _021_;
  wire _022_;
  wire _023_;
  wire _024_;
  wire _025_;
  wire _026_;
  wire _027_;
  wire _028_;
  wire _029_;
  wire _030_;
  wire _031_;
  wire _032_;
  wire _033_;
  wire _034_;
  wire _035_;
  wire _036_;
  wire _037_;
  wire _038_;
  wire _039_;
  wire _040_;
  wire _041_;
  wire _042_;
  wire _043_;
  wire _044_;
  wire _045_;
  wire _046_;
  wire _047_;
  wire _048_;
  wire _049_;
  wire _050_;
  wire _051_;
  wire _052_;
  wire _053_;
  wire _054_;
  wire _055_;
  wire _056_;
  wire _057_;
  wire _058_;
  wire _059_;
  wire _060_;
  wire _061_;
  wire _062_;
  wire _063_;
  wire _064_;
  wire _065_;
  wire _066_;
  wire _067_;
  wire _068_;
  wire _069_;
  wire _070_;
  wire _071_;
  wire _072_;
  wire _073_;
  wire _074_;
  wire _075_;
  wire _076_;
  wire _077_;
  wire _078_;
  wire _079_;
  wire _080_;
  wire _081_;
  wire _082_;
  wire _083_;
  wire _084_;
  wire _085_;
  wire _086_;
  wire _087_;
  wire _088_;
  wire _089_;
  wire _090_;
  wire _091_;
  wire _092_;
  wire _093_;
  wire _094_;
  wire _095_;
  wire _096_;
  wire _097_;
  wire _098_;
  wire _099_;
  wire _100_;
  wire _101_;
  wire _102_;
  wire _103_;
  wire _104_;
  wire _105_;
  wire _106_;
  wire _107_;
  wire _108_;
  wire _109_;
  wire _110_;
  wire _111_;
  wire _112_;
  wire _113_;
  wire _114_;
  wire _115_;
  wire _116_;
  wire _117_;
  wire _118_;
  wire _119_;
  wire _120_;
  wire _121_;
  wire _122_;
  wire _123_;
  wire _124_;
  wire _125_;
  wire _126_;
  wire _127_;
  wire _128_;
  wire _129_;
  wire _130_;
  wire _131_;
  wire _132_;
  wire _133_;
  wire _134_;
  wire _135_;
  wire _136_;
  wire _137_;
  wire _138_;
  wire _139_;
  wire _140_;
  wire _141_;
  wire _142_;
  wire _143_;
  wire _144_;
  wire _145_;
  wire _146_;
  wire _147_;
  wire _148_;
  wire _149_;
  wire _150_;
  wire _151_;
  wire _152_;
  wire _153_;
  wire _154_;
  wire _155_;
  wire _156_;
  wire _157_;
  wire _158_;
  wire _159_;
  wire ERROR;
  wire NOT_EVEN_1;
  wire ONES;
  wire OVERFLOW;
  wire [31:0] i;
  input [3:0] i_arg_A;
  wire [3:0] i_arg_A;
  input [3:0] i_arg_B;
  wire [3:0] i_arg_B;
  input i_clk;
  wire i_clk;
  input [1:0] i_op;
  wire [1:0] i_op;
  input i_reset;
  wire i_reset;
  output [3:0] o_result;
  reg [3:0] o_result;
  output [3:0] o_status;
  reg [3:0] o_status;
  wire [3:0] s_result;
  assign _080_ = ~i_arg_B[2];
  assign _081_ = ~i_arg_B[1];
  assign _082_ = ~i_arg_B[3];
  assign _083_ = ~i_arg_A[3];
  assign _084_ = ~i_arg_A[2];
  assign _085_ = ~i_arg_B[0];
  assign _086_ = ~i_arg_A[1];
  assign _087_ = ~i_arg_A[0];
  assign _088_ = ~i_op[0];
  assign _089_ = ~i_op[1];
  assign _090_ = _088_ & _089_;
  assign _091_ = i_op[0] | i_op[1];
  assign _092_ = i_arg_B[0] | i_arg_A[1];
  assign _093_ = i_arg_B[0] & _087_;
  assign _094_ = _085_ | i_arg_A[0];
  assign _095_ = _082_ & _092_;
  assign _096_ = _094_ & _095_;
  assign _097_ = _080_ & i_arg_B[1];
  assign _098_ = _096_ & _097_;
  assign _099_ = _080_ & _081_;
  assign _100_ = i_arg_B[1] | i_arg_B[0];
  assign _101_ = _085_ & _099_;
  assign _102_ = i_arg_B[3] | _101_;
  assign _103_ = i_arg_A[3] & _102_;
  assign _104_ = _082_ & i_arg_A[2];
  assign _105_ = i_arg_B[0] & _104_;
  assign _106_ = _099_ & _105_;
  assign _107_ = _103_ | _106_;
  assign _108_ = _098_ | _107_;
  assign _109_ = _090_ & _108_;
  assign _110_ = i_arg_B[2] & _084_;
  assign _111_ = _080_ | i_arg_A[2];
  assign _112_ = i_arg_B[2] | i_arg_A[2];
  assign _113_ = i_arg_B[2] & i_arg_A[2];
  assign _114_ = i_arg_B[2] ^ i_arg_A[2];
  assign _115_ = ~_114_;
  assign _116_ = i_arg_B[1] & _086_;
  assign _117_ = _081_ | i_arg_A[1];
  assign _118_ = _085_ & i_arg_A[0];
  assign _119_ = i_arg_B[0] | _087_;
  assign _120_ = _081_ & i_arg_A[1];
  assign _121_ = i_arg_B[1] | _086_;
  assign _122_ = _118_ | _120_;
  assign _123_ = _117_ & _118_;
  assign _124_ = _116_ | _119_;
  assign _125_ = _115_ & _121_;
  assign _126_ = _114_ | _120_;
  assign _127_ = _124_ & _125_;
  assign _128_ = _123_ | _126_;
  assign _129_ = _111_ & _128_;
  assign _130_ = _110_ | _127_;
  assign _131_ = _093_ | _116_;
  assign _132_ = _114_ | _131_;
  assign _133_ = _122_ | _132_;
  assign _134_ = _130_ & _133_;
  assign _135_ = i_op[0] & _089_;
  assign _136_ = ~_135_;
  assign _137_ = i_arg_B[3] & _083_;
  assign _138_ = _135_ & _137_;
  assign _139_ = _134_ & _138_;
  assign _140_ = i_op[0] & i_op[1];
  assign _141_ = i_arg_A[3] & _140_;
  assign _142_ = i_arg_B[2] & i_arg_B[1];
  assign _143_ = i_arg_B[0] & _142_;
  assign _144_ = ~_143_;
  assign _145_ = i_arg_A[1] | i_arg_A[0];
  assign _146_ = i_arg_A[2] | _145_;
  assign _147_ = ~_146_;
  assign _148_ = _088_ & i_op[1];
  assign _149_ = _146_ & _148_;
  assign _150_ = _144_ & _149_;
  assign _151_ = _082_ ^ i_arg_A[3];
  assign _152_ = _150_ & _151_;
  assign _153_ = _141_ | _152_;
  assign _154_ = _139_ | _153_;
  assign s_result[3] = _109_ | _154_;
  assign _155_ = i_arg_B[3] & _084_;
  assign _156_ = _082_ | i_arg_A[2];
  assign _157_ = _134_ & _155_;
  assign _158_ = _083_ & i_arg_A[2];
  assign _159_ = _128_ & _158_;
  assign _000_ = _157_ | _159_;
  assign _001_ = _135_ & _000_;
  assign _002_ = i_arg_A[2] & _101_;
  assign _003_ = _080_ & _100_;
  assign _004_ = _122_ & _003_;
  assign _005_ = i_arg_B[3] | _004_;
  assign _006_ = _002_ | _005_;
  assign _007_ = _090_ & _156_;
  assign _008_ = _006_ & _007_;
  assign _009_ = i_arg_B[1] & i_arg_A[2];
  assign _010_ = ~_009_;
  assign _011_ = _080_ | i_arg_B[0];
  assign _012_ = ~_011_;
  assign _013_ = _009_ & _012_;
  assign _014_ = _010_ | _011_;
  assign _015_ = _149_ & _013_;
  assign _016_ = i_arg_A[3] & _145_;
  assign _017_ = i_arg_A[2] ^ _016_;
  assign _018_ = _140_ & _017_;
  assign _019_ = _015_ | _018_;
  assign _020_ = _008_ | _019_;
  assign s_result[2] = _001_ | _020_;
  assign _021_ = i_arg_B[3] & _134_;
  assign _022_ = i_arg_A[1] | _021_;
  assign _023_ = _083_ & _129_;
  assign _024_ = _086_ | _023_;
  assign _025_ = _135_ & _024_;
  assign _026_ = _022_ & _025_;
  assign _027_ = i_arg_B[3] & i_arg_A[1];
  assign _028_ = _096_ & _099_;
  assign _029_ = _027_ | _028_;
  assign _030_ = _090_ & _029_;
  assign _031_ = i_arg_A[3] & i_arg_A[0];
  assign _032_ = i_arg_A[1] & _031_;
  assign _033_ = ~_032_;
  assign _034_ = i_arg_A[1] | _031_;
  assign _035_ = _140_ & _034_;
  assign _036_ = _033_ & _035_;
  assign _037_ = _009_ & _011_;
  assign _038_ = _113_ | _142_;
  assign _039_ = _092_ & _038_;
  assign _040_ = ~_039_;
  assign _041_ = _037_ | _040_;
  assign _042_ = ~_041_;
  assign _043_ = _150_ & _042_;
  assign _044_ = _036_ | _043_;
  assign _045_ = _030_ | _044_;
  assign s_result[1] = _026_ | _045_;
  assign _046_ = i_arg_A[0] & i_op[0];
  assign _047_ = _089_ | _046_;
  assign _048_ = _087_ & _021_;
  assign _049_ = i_arg_A[0] & _023_;
  assign _050_ = _136_ | _049_;
  assign _051_ = _048_ | _050_;
  assign _052_ = _047_ & _051_;
  assign _053_ = i_arg_B[0] | _041_;
  assign _054_ = i_arg_B[0] | i_arg_A[0];
  assign _055_ = i_arg_B[1] | _054_;
  assign _056_ = i_arg_A[1] & _055_;
  assign _057_ = _053_ & _056_;
  assign _058_ = _113_ & _014_;
  assign _059_ = _041_ & _058_;
  assign _060_ = i_arg_B[1] & _054_;
  assign _061_ = _059_ | _060_;
  assign _062_ = _057_ | _061_;
  assign _063_ = _112_ & _150_;
  assign _064_ = _062_ & _063_;
  assign _065_ = _052_ | _064_;
  assign _066_ = i_arg_A[0] & _102_;
  assign _067_ = _091_ | _066_;
  assign s_result[0] = _065_ & _067_;
  assign OVERFLOW = _141_ & _147_;
  assign _068_ = _143_ & _149_;
  assign _069_ = OVERFLOW | _068_;
  assign _070_ = ~_069_;
  assign _071_ = _082_ | _091_;
  assign _072_ = _101_ | _071_;
  assign _073_ = _070_ & _072_;
  assign ERROR = ~_073_;
  assign _074_ = s_result[1] & s_result[0];
  assign _075_ = s_result[1] ^ s_result[0];
  assign _076_ = s_result[3] & s_result[2];
  assign _077_ = s_result[3] ^ s_result[2];
  assign _078_ = _075_ ^ _077_;
  assign NOT_EVEN_1 = _073_ & _078_;
  assign _079_ = _073_ & _076_;
  assign ONES = _074_ & _079_;
  always @(posedge i_clk, negedge i_reset)
    if (!i_reset) o_result[0] <= 1'h0;
    else o_result[0] <= s_result[0];
  always @(posedge i_clk, negedge i_reset)
    if (!i_reset) o_result[1] <= 1'h0;
    else o_result[1] <= s_result[1];
  always @(posedge i_clk, negedge i_reset)
    if (!i_reset) o_result[2] <= 1'h0;
    else o_result[2] <= s_result[2];
  always @(posedge i_clk, negedge i_reset)
    if (!i_reset) o_result[3] <= 1'h0;
    else o_result[3] <= s_result[3];
  always @(posedge i_clk, negedge i_reset)
    if (!i_reset) o_status[0] <= 1'h0;
    else o_status[0] <= OVERFLOW;
  always @(posedge i_clk, negedge i_reset)
    if (!i_reset) o_status[1] <= 1'h0;
    else o_status[1] <= ONES;
  always @(posedge i_clk, negedge i_reset)
    if (!i_reset) o_status[2] <= 1'h0;
    else o_status[2] <= NOT_EVEN_1;
  always @(posedge i_clk, negedge i_reset)
    if (!i_reset) o_status[3] <= 1'h0;
    else o_status[3] <= ERROR;
  assign i = 32'd4;
endmodule

arith_unit_26.sv
module arith_unit_26(
	i_op,
    i_arg_A,
    i_arg_B,
    i_clk,
    i_reset,
    o_result,
	o_status);

    parameter WIDTH_M = 4;
    parameter WIDTH_N = 2;

    input  logic  [WIDTH_N-1:0]    i_op;
    input  logic  [WIDTH_M-1:0]    i_arg_A;
    input  logic  [WIDTH_M-1:0]    i_arg_B;
    input  logic  [0:0]            i_clk;
    input  logic  [0:0]            i_reset;
    output logic  [WIDTH_M-1:0]    o_result;
    output logic  [3:0]            o_status;
    
    logic [WIDTH_M-1:0] s_result;
	logic 	ERROR;
	logic 	NOT_EVEN_1;
	logic 	ONES;
	logic 	OVERFLOW;


	int i;
	

    always_comb 

	begin
		OVERFLOW =  0;
		ERROR    =  0;
		NOT_EVEN_1 = 0;
		s_result = 'x;		
		case (i_op)
			2'b00 :	begin                       //  operacja n.1 prezsuniecie i_arg_A 
					    if (i_arg_B[WIDTH_M-1] != 1)
					    begin
							s_result = (i_arg_A << i_arg_B);
						end
					    else if ((i_arg_B[WIDTH_M-1] == 1) & ((i_arg_B << 1) == '0))
						begin 
							s_result = i_arg_A;
						end
						else if (i_arg_B[WIDTH_M-1] == 1)
					    begin
							ERROR = 1;
						    s_result = 'x;
					    end
					    else
					    begin
						    s_result = 'x;
					    end
				    end
			2'b01 : begin 						// operacja n.2 porownanie liczb A > B
					    if ((i_arg_A << 1) > (i_arg_B << 1))	// A>B (po modulu)
					    begin
						    if (i_arg_A[WIDTH_M-1] == 0)
						    begin
							    s_result = i_arg_A;
						    end
							else if (i_arg_A[WIDTH_M-1] == 1)
							begin
							    s_result = '0;
							end
						    else 
						    begin
							    s_result = '0;
						    end
					    end
					    else if ((i_arg_A << 1) < (i_arg_B << 1))	// A<B (po modulu)
					    begin 
						    if (((i_arg_A[WIDTH_M-1] == 1) & (i_arg_B[WIDTH_M-1] == 1)) | ((i_arg_A[WIDTH_M-1] == 0) & (i_arg_B[WIDTH_M-1] == 1)))
						    begin
							    s_result = ~i_arg_A;
						    end
							else if (((i_arg_A[WIDTH_M-1] == 1) & (i_arg_B[WIDTH_M-1] == 0)) | ((i_arg_A[WIDTH_M-1] == 0) & (i_arg_B[WIDTH_M-1] == 0)))
							begin
							    s_result = '0;
						    end
						    else 
						    begin	
							    s_result = '0;
						    end
					    end 
					    else 
					    begin
						    s_result = '0;
					    end
				    end
			2'b10 : begin
				        s_result =  'x;
						 // operacja n.3 Dzielenie A/~B
				        if ((((~i_arg_B) << 1) != '0) & ((i_arg_A << 1) != '0)) 
					    begin
							s_result = {(i_arg_A[WIDTH_M-1] ^ (~i_arg_B[WIDTH_M-1])), (i_arg_A[WIDTH_M-2:0] / (~i_arg_B[WIDTH_M-2:0]))};
							
						end 
						else if ((i_arg_A << 1) == '0)
						begin 
							s_result = '0; //0
						end 
						else if (((~i_arg_B) << 1) == '0)
					    begin
						    s_result = 'x;
							ERROR = 1;
					    end
					    else
					    begin
						    s_result = 'x;
					    end
				    end		
			2'b11 : begin 			
						    s_result = 'bx;			// operacja n.4 ZM(A) -> U2(A)
					    if (i_arg_A[WIDTH_M-1] == 0)  
						begin		
						    s_result = i_arg_A;  
						end   
					    else if ((i_arg_A[WIDTH_M-1] == 1) & ((i_arg_A << 1) == '0)) 
						    begin
						        s_result = 'bx;			
						        ERROR = 1;
								OVERFLOW = 1;			// blad i przepelnienie
						    end 
					    else if (i_arg_A[WIDTH_M-1] == 1)
						    begin
						        s_result = (i_arg_A - 'b1);
						        s_result[WIDTH_M-1] = ~i_arg_A[WIDTH_M-1];
						        s_result = ~s_result;
						    end
					    else 
						    begin
						        s_result = 'x;		     	// force else
						    end
				    end
		    default : s_result = 'x;  
		endcase
	

	if (s_result == '1 )
		begin 
		ONES = 1'b1;
		end
	else if (s_result != '0)
		begin
		ONES = 0;
		end
	else 
		begin
		ONES = 0; 
		end	


	for (i = 0; i <WIDTH_M; i = i+1)
	begin
		if (s_result[i] == 1)
			begin
			NOT_EVEN_1 = ~NOT_EVEN_1;	
			end
		else if (s_result[i] != 1)
			begin
			NOT_EVEN_1 = NOT_EVEN_1;
			end
		else 
			begin 
			NOT_EVEN_1 = NOT_EVEN_1;
			end
	end

	begin
		if (ERROR == 1)
			begin
			ONES = 0;
			NOT_EVEN_1 = 0;
			end
		else if (ERROR == 0)
			begin
			NOT_EVEN_1 = NOT_EVEN_1;
			ONES = ONES;
			end
		else 
			begin 
			NOT_EVEN_1 = NOT_EVEN_1;
			ONES = ONES;
			end
	end
	
	end
    

always @(posedge i_clk,negedge i_reset)
	begin 
		if (i_reset == 0) 
		begin 
			o_status = '0;
			o_result = '0;
		end 
		else 
		begin 
			o_result <= s_result;
			o_status <= {ERROR, NOT_EVEN_1, ONES, OVERFLOW};
		end
	end

endmodule

testbench.sv
`timescale 1ns/100ps
module testbench;

parameter M_WIDTH = 4;
parameter N_WIDTH = 2;

        logic             i_clk;
        logic             i_reset;

        logic [M_WIDTH-1:0] i_arg_A_s;	
        logic [M_WIDTH-1:0] i_arg_B_s;
        logic [N_WIDTH-1:0] i_op_s;
        
	    logic [M_WIDTH-1:0] o_result_s, o_result_ss;
		logic [3:0] o_status_s;
		logic [3:0] o_status_ss;


arith_unit_26 	#(.WIDTH_M(M_WIDTH), .WIDTH_N(N_WIDTH))	arith_model	(.i_arg_A(i_arg_A_s), .i_arg_B(i_arg_B_s), .i_op(i_op_s), .o_result(o_result_s)	, .i_clk, .i_reset, .o_status(o_status_s));		
arith_unit_26_rtl 				arith_synth 	(.i_arg_A(i_arg_A_s), .i_arg_B(i_arg_B_s), .i_op(i_op_s), .o_result(o_result_ss), .i_clk, .i_reset, .o_status(o_status_ss));	

initial
        begin
                $dumpfile("signals.vcd");
                $dumpvars(0,testbench);
	
		i_clk = 0; i_reset = 1;               
		i_op_s = 'b00;
		i_arg_A_s = 'b0001;  i_arg_B_s = 'b0000;
		i_clk = 0;
		#1 
		i_clk = 1;#1
		i_clk= 0; i_arg_B_s = 'b1000;
		#1
		i_clk = 1;#1
		i_clk = 0; i_arg_B_s = 'b0010;
		#1
		i_clk = 1;#1
		i_clk = 0; i_arg_B_s = 'b0011;
		#1
		i_clk = 1;#1
		i_clk = 0; i_arg_B_s = 'b0100;
		#1
		i_clk = 1;#1
		i_clk = 0; i_arg_A_s = 'b1110;  i_arg_B_s = 'b0001;
		#1  
		i_clk = 1;#1				// end 00
		i_clk = 0; i_op_s = 01; i_arg_A_s ='b0001; i_arg_B_s = 'b0000;
		#1
		i_clk = 1;#1
		i_clk = 0; i_arg_A_s = 'b1000;
		#1
		i_clk = 1;#1 
		i_clk = 0; i_arg_B_s = 'b0010; 
		#1
		i_clk = 1;#1
		i_clk = 0; i_arg_A_s ='b0101; i_arg_B_s = 'b0100; 
		#1
		i_clk = 1; #1
		i_clk = 0; i_arg_B_s = 'b1111;
	    #1
		i_clk = 1; #1
		i_clk = 0; i_arg_A_s = 'b1010; 	i_arg_B_s = 'b0001; 
		#1
		i_clk = 1;#1				// end 01
		i_clk = 0; i_op_s = 'b10; i_arg_A_s = 'b0110; i_arg_B_s = 'b1111;  		
		#1 
		i_clk = 1;#1
		i_clk = 0; i_arg_B_s = 'b0001;
		#1
		i_clk = 1;#1
        i_clk = 0; i_arg_A_s = 'b1011; i_arg_B_s = 'b1011;
		#1
		i_clk = 1;#1
        i_clk = 0; i_arg_A_s = 'b0100; i_arg_B_s = 'b1101;
		#1
		i_clk = 1;#1
        i_clk = 0; i_arg_A_s = 'b0110; i_arg_B_s = 'b1100;
		#1				
		i_clk = 1;#1				// end 10
        i_clk = 0; i_arg_A_s = 'b0000; i_op_s = 'b11;
		#1
		i_clk = 1;#1                            
        i_clk = 0; i_arg_A_s = 'b0001; 
        #1
		i_clk = 1;#1                                     
        i_clk = 0; i_arg_A_s = 'b1000;
        #1
		i_clk = 1;#1                                     
        i_clk = 0; i_arg_A_s = 'b1110;
        #1
		i_clk = 1;#1                                     
        i_clk = 0;
        #1
		i_clk = 1;#1
		i_clk = 0; i_reset = 0; 
		#1

                $finish;
        end
endmodule

signals.vcd
$date
	Tue Dec 19 00:57:17 2023
$end
$version
	Icarus Verilog
$end
$timescale
	100ps
$end
$scope module testbench $end
$var wire 4 ! o_status_ss [3:0] $end
$var wire 4 " o_status_s [3:0] $end
$var wire 4 # o_result_ss [3:0] $end
$var wire 4 $ o_result_s [3:0] $end
$var parameter 32 % M_WIDTH $end
$var parameter 32 & N_WIDTH $end
$var reg 4 ' i_arg_A_s [3:0] $end
$var reg 4 ( i_arg_B_s [3:0] $end
$var reg 1 ) i_clk $end
$var reg 2 * i_op_s [1:0] $end
$var reg 1 + i_reset $end
$scope module arith_model $end
$var wire 4 , i_arg_A [3:0] $end
$var wire 4 - i_arg_B [3:0] $end
$var wire 1 ) i_clk $end
$var wire 2 . i_op [1:0] $end
$var wire 1 + i_reset $end
$var parameter 32 / WIDTH_M $end
$var parameter 32 0 WIDTH_N $end
$var reg 1 1 ERROR $end
$var reg 1 2 NOT_EVEN_1 $end
$var reg 1 3 ONES $end
$var reg 1 4 OVERFLOW $end
$var reg 4 5 o_result [3:0] $end
$var reg 4 6 o_status [3:0] $end
$var reg 4 7 s_result [3:0] $end
$var integer 32 8 i [31:0] $end
$upscope $end
$scope module arith_synth $end
$var wire 1 9 ERROR $end
$var wire 1 : NOT_EVEN_1 $end
$var wire 1 ; ONES $end
$var wire 1 < OVERFLOW $end
$var wire 1 = _000_ $end
$var wire 1 > _001_ $end
$var wire 1 ? _002_ $end
$var wire 1 @ _003_ $end
$var wire 1 A _004_ $end
$var wire 1 B _005_ $end
$var wire 1 C _006_ $end
$var wire 1 D _007_ $end
$var wire 1 E _008_ $end
$var wire 1 F _009_ $end
$var wire 1 G _010_ $end
$var wire 1 H _011_ $end
$var wire 1 I _012_ $end
$var wire 1 J _013_ $end
$var wire 1 K _014_ $end
$var wire 1 L _015_ $end
$var wire 1 M _016_ $end
$var wire 1 N _017_ $end
$var wire 1 O _018_ $end
$var wire 1 P _019_ $end
$var wire 1 Q _020_ $end
$var wire 1 R _021_ $end
$var wire 1 S _022_ $end
$var wire 1 T _023_ $end
$var wire 1 U _024_ $end
$var wire 1 V _025_ $end
$var wire 1 W _026_ $end
$var wire 1 X _027_ $end
$var wire 1 Y _028_ $end
$var wire 1 Z _029_ $end
$var wire 1 [ _030_ $end
$var wire 1 \ _031_ $end
$var wire 1 ] _032_ $end
$var wire 1 ^ _033_ $end
$var wire 1 _ _034_ $end
$var wire 1 ` _035_ $end
$var wire 1 a _036_ $end
$var wire 1 b _037_ $end
$var wire 1 c _038_ $end
$var wire 1 d _039_ $end
$var wire 1 e _040_ $end
$var wire 1 f _041_ $end
$var wire 1 g _042_ $end
$var wire 1 h _043_ $end
$var wire 1 i _044_ $end
$var wire 1 j _045_ $end
$var wire 1 k _046_ $end
$var wire 1 l _047_ $end
$var wire 1 m _048_ $end
$var wire 1 n _049_ $end
$var wire 1 o _050_ $end
$var wire 1 p _051_ $end
$var wire 1 q _052_ $end
$var wire 1 r _053_ $end
$var wire 1 s _054_ $end
$var wire 1 t _055_ $end
$var wire 1 u _056_ $end
$var wire 1 v _057_ $end
$var wire 1 w _058_ $end
$var wire 1 x _059_ $end
$var wire 1 y _060_ $end
$var wire 1 z _061_ $end
$var wire 1 { _062_ $end
$var wire 1 | _063_ $end
$var wire 1 } _064_ $end
$var wire 1 ~ _065_ $end
$var wire 1 !" _066_ $end
$var wire 1 "" _067_ $end
$var wire 1 #" _068_ $end
$var wire 1 $" _069_ $end
$var wire 1 %" _070_ $end
$var wire 1 &" _071_ $end
$var wire 1 '" _072_ $end
$var wire 1 (" _073_ $end
$var wire 1 )" _074_ $end
$var wire 1 *" _075_ $end
$var wire 1 +" _076_ $end
$var wire 1 ," _077_ $end
$var wire 1 -" _078_ $end
$var wire 1 ." _079_ $end
$var wire 1 /" _080_ $end
$var wire 1 0" _081_ $end
$var wire 1 1" _082_ $end
$var wire 1 2" _083_ $end
$var wire 1 3" _084_ $end
$var wire 1 4" _085_ $end
$var wire 1 5" _086_ $end
$var wire 1 6" _087_ $end
$var wire 1 7" _088_ $end
$var wire 1 8" _089_ $end
$var wire 1 9" _090_ $end
$var wire 1 :" _091_ $end
$var wire 1 ;" _092_ $end
$var wire 1 <" _093_ $end
$var wire 1 =" _094_ $end
$var wire 1 >" _095_ $end
$var wire 1 ?" _096_ $end
$var wire 1 @" _097_ $end
$var wire 1 A" _098_ $end
$var wire 1 B" _099_ $end
$var wire 1 C" _100_ $end
$var wire 1 D" _101_ $end
$var wire 1 E" _102_ $end
$var wire 1 F" _103_ $end
$var wire 1 G" _104_ $end
$var wire 1 H" _105_ $end
$var wire 1 I" _106_ $end
$var wire 1 J" _107_ $end
$var wire 1 K" _108_ $end
$var wire 1 L" _109_ $end
$var wire 1 M" _110_ $end
$var wire 1 N" _111_ $end
$var wire 1 O" _112_ $end
$var wire 1 P" _113_ $end
$var wire 1 Q" _114_ $end
$var wire 1 R" _115_ $end
$var wire 1 S" _116_ $end
$var wire 1 T" _117_ $end
$var wire 1 U" _118_ $end
$var wire 1 V" _119_ $end
$var wire 1 W" _120_ $end
$var wire 1 X" _121_ $end
$var wire 1 Y" _122_ $end
$var wire 1 Z" _123_ $end
$var wire 1 [" _124_ $end
$var wire 1 \" _125_ $end
$var wire 1 ]" _126_ $end
$var wire 1 ^" _127_ $end
$var wire 1 _" _128_ $end
$var wire 1 `" _129_ $end
$var wire 1 a" _130_ $end
$var wire 1 b" _131_ $end
$var wire 1 c" _132_ $end
$var wire 1 d" _133_ $end
$var wire 1 e" _134_ $end
$var wire 1 f" _135_ $end
$var wire 1 g" _136_ $end
$var wire 1 h" _137_ $end
$var wire 1 i" _138_ $end
$var wire 1 j" _139_ $end
$var wire 1 k" _140_ $end
$var wire 1 l" _141_ $end
$var wire 1 m" _142_ $end
$var wire 1 n" _143_ $end
$var wire 1 o" _144_ $end
$var wire 1 p" _145_ $end
$var wire 1 q" _146_ $end
$var wire 1 r" _147_ $end
$var wire 1 s" _148_ $end
$var wire 1 t" _149_ $end
$var wire 1 u" _150_ $end
$var wire 1 v" _151_ $end
$var wire 1 w" _152_ $end
$var wire 1 x" _153_ $end
$var wire 1 y" _154_ $end
$var wire 1 z" _155_ $end
$var wire 1 {" _156_ $end
$var wire 1 |" _157_ $end
$var wire 1 }" _158_ $end
$var wire 1 ~" _159_ $end
$var wire 32 !# i [31:0] $end
$var wire 4 "# i_arg_A [3:0] $end
$var wire 4 ## i_arg_B [3:0] $end
$var wire 1 ) i_clk $end
$var wire 2 $# i_op [1:0] $end
$var wire 1 + i_reset $end
$var wire 4 %# s_result [3:0] $end
$var reg 4 &# o_result [3:0] $end
$var reg 4 '# o_status [3:0] $end
$upscope $end
$upscope $end
$enddefinitions $end
$comment Show the parameter values. $end
$dumpall
b10 0
b100 /
b10 &
b100 %
$end
#0
$dumpvars
bx '#
bx &#
b1 %#
b0 $#
b0 ##
b1 "#
b100 !#
0~"
0}"
0|"
1{"
0z"
0y"
0x"
0w"
1v"
0u"
0t"
0s"
0r"
1q"
1p"
1o"
0n"
0m"
0l"
0k"
0j"
0i"
0h"
1g"
0f"
0e"
1d"
0c"
0b"
0a"
1`"
1_"
0^"
0]"
1\"
0["
1Z"
1Y"
1X"
0W"
0V"
1U"
1T"
0S"
1R"
0Q"
0P"
0O"
1N"
0M"
0L"
0K"
0J"
0I"
0H"
0G"
0F"
1E"
1D"
0C"
1B"
0A"
0@"
0?"
0>"
1="
0<"
0;"
0:"
19"
18"
17"
06"
15"
14"
13"
12"
11"
10"
1/"
0."
1-"
0,"
0+"
1*"
0)"
1("
1'"
1&"
1%"
0$"
0#"
1""
1!"
1~
0}
0|
0{
0z
0y
0x
0w
0v
0u
1t
1s
1r
1q
1p
1o
1n
0m
1l
0k
0j
0i
0h
0g
1f
1e
0d
0c
0b
0a
0`
0_
1^
0]
0\
0[
0Z
0Y
0X
0W
0V
1U
1T
0S
0R
0Q
0P
0O
0N
0M
0L
1K
0J
0I
1H
1G
0F
0E
1D
0C
0B
0A
0@
0?
0>
0=
0<
0;
1:
09
b100 8
b1 7
bx 6
bx 5
04
03
12
01
b0 .
b0 -
b1 ,
1+
b0 *
0)
b0 (
b1 '
bx $
bx #
bx "
bx !
$end
#10
b100 "
b100 6
b1 $
b1 5
b1 #
b1 &#
b100 !
b100 '#
1)
#20
1:
1-"
0,"
b1 %#
0Q
0D
0E
0v"
0{"
0&"
1C
01"
1h"
1z"
1B
b100 8
b1 7
12
b1000 (
b1000 -
b1000 ##
0)
#30
1)
#40
1,"
0*"
b100 %#
0n
1Q
0""
0T
1E
0!"
0`"
1e"
0E"
0_"
1a"
0D"
0Z"
1D
1A
1^"
1c"
1{
0B"
0T"
1v"
1{"
1&"
1@
1["
1b"
1C
1z
00"
11"
1@"
1C"
1S"
0h"
0z"
1B
1y
b100 8
b100 7
12
b10 (
b10 -
b10 ##
0)
#50
b100 $
b100 5
b100 #
b100 &#
1)
#60
1:
0."
1-"
0+"
1,"
0Q
0E
b1000 %#
0C
1L"
0B
1K"
0A
1A"
0Y"
1?"
0U"
1>"
04"
1;"
1V"
b100 8
b1000 7
12
b11 (
b11 -
b11 ##
0)
#70
b1000 #
b1000 &#
b1000 $
b1000 5
1)
#80
0:
0-"
0,"
b0 %#
0L"
1I
1Y"
1Z"
0?"
0K"
0\"
1_"
0^"
0{
0N"
0H
1T"
1U"
0>"
0A"
0@
0R"
1]"
0b"
0["
0z
0/"
10"
14"
0;"
0@"
0C"
1M"
1O"
1Q"
0S"
0V"
0y
b100 8
b0 7
02
b100 (
b100 -
b100 ##
0)
#90
b0 "
b0 6
b0 $
b0 5
b0 #
b0 &#
b0 !
b0 '#
1)
#100
1."
1+"
b1100 %#
1Q
1L"
1E
1K"
1C
1J"
1B
1I"
1A
0e"
0=
1{
1B"
0="
1b"
1@
0a"
1["
0I
0X"
0U
1>"
1`"
0Z"
0~"
1v
1/"
04"
1<"
1C"
1H"
0M"
1V"
1H
02"
03"
05"
16"
1;"
1G"
1N"
0U"
1W"
0v"
0}"
1M
0N
1S
1_
1u
02
b100 8
b1100 7
b1 (
b1 -
b1 ##
b1110 '
b1110 ,
b1110 "#
0)
#110
b1100 #
b1100 &#
b1100 $
b1100 5
1)
